smischlib.py
src/console/clear_console.py
src/input/anim_input.py
src/input/ask_input.py
src/numbersys/bin_to_text.py
src/numbersys/text_to_bin.py
src/print/anim_print.py
src/string/palindrom.py
src/utilities/running_os.py
smischlib-1.0.10.dist-info/METADATA
smischlib-1.0.10.dist-info/WHEEL
smischlib-1.0.10.dist-info/top_level.txt
smischlib-1.0.10.dist-info/RECORD
