Metadata-Version: 2.1
Name: smischlib
Version: 1.0.10
Summary: Library with addon functions for python.
Author: Smisch
Author-email: smisch@smisch.sk
License: MIT
Keywords: print input
